Metadata-Version: 2.1
Name: pythonhost
Version: 1.0.2
Summary: pythonhost Library
Home-page: https://pythonhost.ir
Download-URL: https://github.com/pythonhost/pythonhost.git
Author: pythonhost Co
Author-email: info@pythonhost.ir
License: MIT
Keywords: pythonhost pythonhost.ir ftp python host
Platform: any
Classifier: Programming Language :: Python :: 3
Classifier: License :: OSI Approved :: MIT License
Classifier: Operating System :: OS Independent
Classifier: Development Status :: 4 - Beta
Classifier: Intended Audience :: Developers
Classifier: Environment :: Console
Classifier: Topic :: Software Development :: Libraries :: Python Modules
